aules_dropout_control/__init__.py
aules_dropout_control/__main__.py
aules_dropout_control/webscraper.py
aules_dropout_control-0.1.1.dist-info/METADATA
aules_dropout_control-0.1.1.dist-info/WHEEL
aules_dropout_control-0.1.1.dist-info/entry_points.txt
aules_dropout_control-0.1.1.dist-info/RECORD
