Metadata-Version: 2.3
Name: aules-dropout-control
Version: 0.1.1
Summary: Utilidad para obtener los alumnos que no se han conectado en un número de días a Aules. Se pueden obtener varios cursos simultáneamente.
License: GPL-3.0-or-later
Author: Alvaro Maceda
Author-email: alvaro.maceda@email.com
Requires-Python: >=3.8,<4.0
Classifier: License :: OSI Approved :: GNU General Public License v3 or later (GPLv3+)
Classifier: Programming Language :: Python :: 3
Classifier: Programming Language :: Python :: 3.8
Classifier: Programming Language :: Python :: 3.9
Classifier: Programming Language :: Python :: 3.10
Classifier: Programming Language :: Python :: 3.11
Classifier: Programming Language :: Python :: 3.12
Classifier: Programming Language :: Python :: 3.13
Requires-Dist: beautifulsoup4 (>=4.12.2,<5.0.0)
Requires-Dist: requests (>=2.31.0,<3.0.0)
